driwecore
